MANIFEST.in
README.rst
setup.py
pybb/__init__.py
pybb/base.py
pybb/compat.py
pybb/constants.py
pybb/context_processors.py
pybb/decorators.py
pybb/defaults.py
pybb/feeds.py
pybb/fields.py
pybb/filters.py
pybb/helpers.py
pybb/mixins.py
pybb/processors.py
pybb/proxies.py
pybb/receivers.py
pybb/sanitizer.py
pybb/subscription.py
pybb/tasks.py
pybb/urls.py
pybb/util.py
pybb/contrib/__init__.py
pybb/contrib/ban/__init__.py
pybb/contrib/ban/compat.py
pybb/contrib/ban/forms.py
pybb/contrib/ban/middleware.py
pybb/contrib/ban/models.py
pybb/contrib/ban/settings.py
pybb/contrib/ban/tests.py
pybb/contrib/ban/urls.py
pybb/contrib/ban/util.py
pybb/contrib/ban/views.py
pybb/contrib/mentions/__init__.py
pybb/contrib/mentions/formatters.py
pybb/contrib/mentions/models.py
pybb/contrib/mentions/processors.py
pybb/contrib/mentions/settings.py
pybb/contrib/mentions/signals.py
pybb/contrib/mentions/tests.py
pybb/contrib/mentions/views.py
pybb/contrib/profiles/__init__.py
pybb/contrib/profiles/forms.py
pybb/contrib/profiles/middleware.py
pybb/contrib/profiles/models.py
pybb/contrib/profiles/urls.py
pybb/contrib/profiles/views.py
pybb/contrib/quotes/__init__.py
pybb/contrib/quotes/exceptions.py
pybb/contrib/quotes/formatters.py
pybb/contrib/quotes/models.py
pybb/contrib/quotes/processors.py
pybb/contrib/quotes/settings.py
pybb/contrib/quotes/signals.py
pybb/contrib/quotes/tests.py
pybb/contrib/quotes/urls.py
pybb/contrib/quotes/views.py
pybb/contrib/reports/__init__.py
pybb/contrib/reports/forms.py
pybb/contrib/reports/models.py
pybb/contrib/reports/tests.py
pybb/contrib/reports/urls.py
pybb/contrib/reports/views.py
pybb/contrib/reports/templatetags/__init__.py
pybb/contrib/reports/templatetags/report_tags.py
pybb/engines/__init__.py
pybb/engines/base.py
pybb/engines/markdown.py
pybb/engines/bbcode/__init__.py
pybb/engines/bbcode/formatters.py
pybb/forms/__init__.py
pybb/forms/base.py
pybb/management/__init__.py
pybb/management/commands/__init__.py
pybb/management/commands/dump_topics.py
pybbm_fork.egg-info/PKG-INFO
pybbm_fork.egg-info/SOURCES.txt
pybbm_fork.egg-info/dependency_links.txt
pybbm_fork.egg-info/top_level.txt
