Metadata-Version: 1.1
Name: pybbm-fork
Version: 0.15.0
Summary: PyBB modified. Django forum application
Home-page: UNKNOWN
Author: Florent Messa
Author-email: florent.messa@gmail.com
License: BSD
Keywords: django application forum board
Platform: UNKNOWN
Classifier: Development Status :: 4 - Beta
Classifier: Environment :: Web Environment
Classifier: Framework :: Django
Classifier: Intended Audience :: Developers
Classifier: License :: OSI Approved :: BSD License
Classifier: Operating System :: OS Independent
Classifier: Programming Language :: Python
Classifier: Topic :: Internet :: WWW/HTTP :: Dynamic Content :: Message Boards
Classifier: Topic :: Software Development :: Libraries :: Python Modules
